digquery/__init__.py
digquery/dig_query_types.py
digquery-0.1.7.dist-info/METADATA
digquery-0.1.7.dist-info/WHEEL
digquery-0.1.7.dist-info/entry_points.txt
digquery-0.1.7.dist-info/top_level.txt
digquery-0.1.7.dist-info/RECORD
