Metadata-Version: 2.1
Name: digquery
Version: 0.1.7
Summary: A Python package for querying DNS information using dig
Home-page: https://github.com/techdjay/digquery
Author: Jay
Author-email: techdjay@gmail.com
Classifier: Development Status :: 3 - Alpha
Classifier: Intended Audience :: Developers
Classifier: License :: OSI Approved :: MIT License
Classifier: Programming Language :: Python :: 3
Classifier: Programming Language :: Python :: 3.6
Classifier: Programming Language :: Python :: 3.7
Classifier: Programming Language :: Python :: 3.8
Classifier: Programming Language :: Python :: 3.9
